django_polls_natacha-0.1.0.dist-info/licenses/LICENCE
polls/__init__.py
polls/admin.py
polls/apps.py
polls/models.py
polls/tests.py
polls/urls.py
polls/views.py
polls/migrations/0001_initial.py
polls/migrations/__init__.py
polls/migrations/__pycache__/0001_initial.cpython-310.pyc
polls/migrations/__pycache__/__init__.cpython-310.pyc
polls/templates/polls/detail.html
polls/templates/polls/index.html
django_polls_natacha-0.1.0.dist-info/METADATA
django_polls_natacha-0.1.0.dist-info/WHEEL
django_polls_natacha-0.1.0.dist-info/top_level.txt
django_polls_natacha-0.1.0.dist-info/RECORD
