Metadata-Version: 2.4
Name: django-polls-natacha
Version: 0.1.0
Summary: A reusable Django app for polls
Author: nandja matacha
Author-email: nandjakessianatacha@gmail.com
License: MIT
License-File: LICENCE
Requires-Dist: Django>=3.2
Dynamic: author
Dynamic: author-email
Dynamic: license
Dynamic: license-file
Dynamic: requires-dist
Dynamic: summary
